team/__init__.py
team/admin.py
team/apps.py
team/static/css/team/bethany_ds.css
team/static/css/team/medicio_ds.css
team/static/css/team/medilab_ds.css
team/static/css/team/mentor_ds.css
team/templates/team/_common.html
team/templates/team/bethany_ds.html
team/templates/team/medicio_ds.html
team/templates/team/medilab_ds.html
team/templates/team/mentor_ds.html
team/templatetags/__init__.py
team/templatetags/team_tags.py
django_team_ds-0.1.0.dist-info/LICENSE
django_team_ds-0.1.0.dist-info/METADATA
django_team_ds-0.1.0.dist-info/WHEEL
django_team_ds-0.1.0.dist-info/top_level.txt
django_team_ds-0.1.0.dist-info/RECORD
